{
  "@context": "https://schema.org",
  "@type": "QAPage",
  "mainEntity": {
    "@type": "Question",
    "name": "What to Do When Your Workers' Comp Claim Is Denied: A Guide to the Appeals Process",
    "text": "What to Do When Your Workers' Comp Claim Is Denied: A Guide to the Appeals Process",
    "answerCount": 1,
    "acceptedAnswer": {
      "@type": "Answer",
      "text": "A workplace injury is stressful enough without the added burden of a 'denied claim.' In Utah and Idaho, workers' compensation is designed to be a 'no-fault' system, meaning you should receive benefits regardless of who caused the accident. However, insurance companies frequently deny claims on technicalities or disputed facts. \n\nIf you have received a denial letter, your case isn't over—it’s just entering a new phase. This guide addresses the immediate steps and long-term strategy required to overturn a workers' comp denial.\n\n### Why Was My Claim Denied?\nThe denial letter must state the specific grounds for the rejection. Common reasons include:\n- **Lack of Timely Notice:** In Utah, you generally have 180 days to report a claim, but you should do it immediately. Idaho has stricter notification requirements. If you waited weeks to tell your boss, the insurer will claim the injury happened elsewhere.\n- **No Witness to the Accident:** 'Unwitnessed' injuries are frequently targeted for denial.\n- **Disputed Causation:** The insurance company acknowledges you are hurt but claims the injury was caused by a weekend activity or a previous job, not your current work duties.\n- **The 'Idiosyncratic' Defense:** They claim your body just 'gave out' due to personal health issues rather than an industrial accident.\n\n### What to Do First: The 48-Hour Rule\nWithin 48 hours of receiving a denial, you should:\n1. **Notify your medical providers:** Tell your doctor's billing office that the workers' comp claim was denied. This may allow them to bill your private insurance temporarily so your treatment doesn't stop.\n2. **Secure evidence:** Talk to any coworkers who saw you get hurt or saw you limping/in pain immediately after the shift.\n3. **Request your file:** You have a right to see the information the insurance company used to deny your claim.\n\n### How the Appeals Process Works\nBoth Utah and Idaho have formal systems for appealing a denied claim.\n\n**In Utah:**\nThe appeal begins by filing an 'Application for Hearing' with the Adjudication Division of the Utah Labor Commission. This triggers a legal process that includes 'discovery' (exchanging evidence) and potentially a 'Medical Panel' review if the dispute is about the nature of the injury.\n\n**In Idaho:**\nThe process involves the Idaho Industrial Commission. You must file a 'Complaint' to start the formal litigation. This is a complex legal document; filing it incorrectly can lead to your case being dismissed permanently.\n\n### Key Evidence and Documents\nTo overturn a denial, 'he-said-she-said' won't cut it. You need:\n- **Medical Records:** Specifically, the 'Initial Visit' note. What you told the doctor the very first time you sought treatment is the most important evidence in your case.\n- **Surveillance Footage:** If the injury happened in a shop or retail environment, we need to secure security footage before it is looped over.\n- **Expert Testimony:** We often hire medical experts to review your records and write a report stating that your work activities were the 'preponderance of the cause' of your injury.\n\n### Common Mistakes\n- **Giving a Recorded Statement:** Never give a recorded statement to the insurance adjuster after a denial without an attorney. They are trained to ask 'trap' questions that can make a legitimate injury sound like a pre-existing condition.\n- **Missing Deadlines:** The 'Statute of Limitations' is the deadline for filing your appeal. If you miss this by even one day, you lose your right to benefits forever.\n- **Assuming the HR Department is on Your Side:** HR works for the company. While they may be friendly, their goal is to minimize the company’s liability.\n\n### When to Contact a Lawyer\nYou should seek legal counsel the moment you receive a denial. Attempting to navigate the Labor Commission or Industrial Commission alone is like performing surgery on yourself. The insurance company will have a team of lawyers; you should too.\n\nAt Just Work Comp Law, we represent injured workers in West Valley City, Ogden, St. George, and throughout Idaho. We operate on a 'contingency fee' basis, meaning we only get paid if we successfully recover money for you.\n\n### Summary Checklist and Next Steps\n1. **Read the denial letter carefully:** Identify the 'reason for denial.'\n2. **Gather your medical records:** Especially the first report from the ER or Urgent Care.\n3. **Call Just Work Comp Law at 801-746-0290:** Let us handle the communication with the insurance adjuster.\n4. **File the Appeal:** Do not wait for the insurance company to 'reconsider.' File the formal legal paperwork to protect your rights.\n5. **Continue Treatment:** Do not stop going to the doctor. A gap in treatment is used by insurance companies to argue that you are 'cured.'\n\nWhether you are in Murray, Taylorsville, or Boise, our team—including attorneys Mark J. Sanchez, Jared L. Mortenson, and Blair Jones—is ready to help you turn a 'No' into a 'Yes.'",
      "author": {
        "@type": "Organization",
        "name": "Just Work Comp Law"
      }
    }
  }
}